{
  "head" : {
    "vars" : [ "item", "itemLabel", "instance_of", "subclass_of", "type_of_initiative_tag" ]
  },
  "results" : {
    "bindings" : [ {
      "item" : {
        "type" : "uri",
        "value" : "http://base.transformap.co/entity/Q10"
      },
      "subclass_of" : {
        "type" : "uri",
        "value" : "http://base.transformap.co/entity/Q8"
      },
      "instance_of" : {
        "type" : "uri",
        "value" : "http://base.transformap.co/entity/Q5"
      },
      "itemLabel" : {
        "xml:lang" : "de",
        "type" : "literal",
        "value" : "Fairer Handel (Fair Trade)"
      }
    }, {
      "item" : {
        "type" : "uri",
        "value" : "http://base.transformap.co/entity/Q100"
      },
      "subclass_of" : {
        "type" : "uri",
        "value" : "http://base.transformap.co/entity/Q13"
      },
      "instance_of" : {
        "type" : "uri",
        "value" : "http://base.transformap.co/entity/Q6"
      },
      "type_of_initiative_tag" : {
        "type" : "literal",
        "value" : "Koprades telpa"
      },
      "itemLabel" : {
        "xml:lang" : "de",
        "type" : "literal",
        "value" : "Freiraum, Shared Space"
      }
    }, {
      "item" : {
        "type" : "uri",
        "value" : "http://base.transformap.co/entity/Q101"
      },
      "subclass_of" : {
        "type" : "uri",
        "value" : "http://base.transformap.co/entity/Q13"
      },
      "instance_of" : {
        "type" : "uri",
        "value" : "http://base.transformap.co/entity/Q6"
      },
      "type_of_initiative_tag" : {
        "type" : "literal",
        "value" : "sustainable_mobility"
      },
      "itemLabel" : {
        "xml:lang" : "de",
        "type" : "literal",
        "value" : "Nachhaltige Verkehrsinitiativen"
      }
    }, {
      "item" : {
        "type" : "uri",
        "value" : "http://base.transformap.co/entity/Q102"
      },
      "subclass_of" : {
        "type" : "uri",
        "value" : "http://base.transformap.co/entity/Q13"
      },
      "instance_of" : {
        "type" : "uri",
        "value" : "http://base.transformap.co/entity/Q6"
      },
      "type_of_initiative_tag" : {
        "type" : "literal",
        "value" : "bicycle_selfrepair"
      },
      "itemLabel" : {
        "xml:lang" : "de",
        "type" : "literal",
        "value" : "Fahrrad-Selbsthilfewerkstatt"
      }
    }, {
      "item" : {
        "type" : "uri",
        "value" : "http://base.transformap.co/entity/Q103"
      },
      "subclass_of" : {
        "type" : "uri",
        "value" : "http://base.transformap.co/entity/Q13"
      },
      "instance_of" : {
        "type" : "uri",
        "value" : "http://base.transformap.co/entity/Q6"
      },
      "type_of_initiative_tag" : {
        "type" : "literal",
        "value" : "bicycle_awareness"
      },
      "itemLabel" : {
        "xml:lang" : "de",
        "type" : "literal",
        "value" : "Fahrrad NGO"
      }
    }, {
      "item" : {
        "type" : "uri",
        "value" : "http://base.transformap.co/entity/Q104"
      },
      "subclass_of" : {
        "type" : "uri",
        "value" : "http://base.transformap.co/entity/Q13"
      },
      "instance_of" : {
        "type" : "uri",
        "value" : "http://base.transformap.co/entity/Q6"
      },
      "type_of_initiative_tag" : {
        "type" : "literal",
        "value" : "collective_energy"
      },
      "itemLabel" : {
        "xml:lang" : "de",
        "type" : "literal",
        "value" : "BürgerInnenbeteiligungsanlagen"
      }
    }, {
      "item" : {
        "type" : "uri",
        "value" : "http://base.transformap.co/entity/Q105"
      },
      "subclass_of" : {
        "type" : "uri",
        "value" : "http://base.transformap.co/entity/Q13"
      },
      "instance_of" : {
        "type" : "uri",
        "value" : "http://base.transformap.co/entity/Q6"
      },
      "type_of_initiative_tag" : {
        "type" : "literal",
        "value" : "localcollective_ressources"
      },
      "itemLabel" : {
        "xml:lang" : "de",
        "type" : "literal",
        "value" : "Gemeinschaftseigentum"
      }
    }, {
      "item" : {
        "type" : "uri",
        "value" : "http://base.transformap.co/entity/Q106"
      },
      "subclass_of" : {
        "type" : "uri",
        "value" : "http://base.transformap.co/entity/Q13"
      },
      "instance_of" : {
        "type" : "uri",
        "value" : "http://base.transformap.co/entity/Q6"
      },
      "type_of_initiative_tag" : {
        "type" : "literal",
        "value" : "community_forestry"
      },
      "itemLabel" : {
        "xml:lang" : "de",
        "type" : "literal",
        "value" : "Gemeinschaftswald"
      }
    }, {
      "item" : {
        "type" : "uri",
        "value" : "http://base.transformap.co/entity/Q107"
      },
      "subclass_of" : {
        "type" : "uri",
        "value" : "http://base.transformap.co/entity/Q13"
      },
      "instance_of" : {
        "type" : "uri",
        "value" : "http://base.transformap.co/entity/Q6"
      },
      "type_of_initiative_tag" : {
        "type" : "literal",
        "value" : "other_infraressources"
      },
      "itemLabel" : {
        "xml:lang" : "de",
        "type" : "literal",
        "value" : "Andere (Infrastruktur und Ressourcen)"
      }
    }, {
      "item" : {
        "type" : "uri",
        "value" : "http://base.transformap.co/entity/Q108"
      },
      "subclass_of" : {
        "type" : "uri",
        "value" : "http://base.transformap.co/entity/Q14"
      },
      "instance_of" : {
        "type" : "uri",
        "value" : "http://base.transformap.co/entity/Q6"
      },
      "type_of_initiative_tag" : {
        "type" : "literal",
        "value" : "socialinclusion_employment"
      },
      "itemLabel" : {
        "xml:lang" : "de",
        "type" : "literal",
        "value" : "Sozialökonomische und - integrative Betriebe"
      }
    }, {
      "item" : {
        "type" : "uri",
        "value" : "http://base.transformap.co/entity/Q109"
      },
      "subclass_of" : {
        "type" : "uri",
        "value" : "http://base.transformap.co/entity/Q14"
      },
      "instance_of" : {
        "type" : "uri",
        "value" : "http://base.transformap.co/entity/Q6"
      },
      "type_of_initiative_tag" : {
        "type" : "literal",
        "value" : "socialinclusion_empowerment"
      },
      "itemLabel" : {
        "xml:lang" : "de",
        "type" : "literal",
        "value" : "Soziale Inklusion - Selbstermächtigung"
      }
    }, {
      "item" : {
        "type" : "uri",
        "value" : "http://base.transformap.co/entity/Q11"
      },
      "subclass_of" : {
        "type" : "uri",
        "value" : "http://base.transformap.co/entity/Q8"
      },
      "instance_of" : {
        "type" : "uri",
        "value" : "http://base.transformap.co/entity/Q5"
      },
      "itemLabel" : {
        "xml:lang" : "de",
        "type" : "literal",
        "value" : "Wiederverwenden, -benutzen, reparieren und reduzieren"
      }
    }, {
      "item" : {
        "type" : "uri",
        "value" : "http://base.transformap.co/entity/Q110"
      },
      "subclass_of" : {
        "type" : "uri",
        "value" : "http://base.transformap.co/entity/Q14"
      },
      "instance_of" : {
        "type" : "uri",
        "value" : "http://base.transformap.co/entity/Q6"
      },
      "type_of_initiative_tag" : {
        "type" : "literal",
        "value" : "lowincome_supermarket"
      },
      "itemLabel" : {
        "xml:lang" : "de",
        "type" : "literal",
        "value" : "Sozialmarkt"
      }
    }, {
      "item" : {
        "type" : "uri",
        "value" : "http://base.transformap.co/entity/Q111"
      },
      "subclass_of" : {
        "type" : "uri",
        "value" : "http://base.transformap.co/entity/Q14"
      },
      "instance_of" : {
        "type" : "uri",
        "value" : "http://base.transformap.co/entity/Q6"
      },
      "type_of_initiative_tag" : {
        "type" : "literal",
        "value" : "foodbank"
      },
      "itemLabel" : {
        "xml:lang" : "de",
        "type" : "literal",
        "value" : "Tafel"
      }
    }, {
      "item" : {
        "type" : "uri",
        "value" : "http://base.transformap.co/entity/Q112"
      },
      "subclass_of" : {
        "type" : "uri",
        "value" : "http://base.transformap.co/entity/Q14"
      },
      "instance_of" : {
        "type" : "uri",
        "value" : "http://base.transformap.co/entity/Q6"
      },
      "type_of_initiative_tag" : {
        "type" : "literal",
        "value" : "homeless_shelter"
      },
      "itemLabel" : {
        "xml:lang" : "de",
        "type" : "literal",
        "value" : "Notschlafstelle"
      }
    }, {
      "item" : {
        "type" : "uri",
        "value" : "http://base.transformap.co/entity/Q113"
      },
      "subclass_of" : {
        "type" : "uri",
        "value" : "http://base.transformap.co/entity/Q14"
      },
      "instance_of" : {
        "type" : "uri",
        "value" : "http://base.transformap.co/entity/Q6"
      },
      "type_of_initiative_tag" : {
        "type" : "literal",
        "value" : "other_socialinclusion"
      },
      "itemLabel" : {
        "xml:lang" : "de",
        "type" : "literal",
        "value" : "Andere (Sozialprojekte)"
      }
    }, {
      "item" : {
        "type" : "uri",
        "value" : "http://base.transformap.co/entity/Q114"
      },
      "subclass_of" : {
        "type" : "uri",
        "value" : "http://base.transformap.co/entity/Q15"
      },
      "instance_of" : {
        "type" : "uri",
        "value" : "http://base.transformap.co/entity/Q6"
      },
      "type_of_initiative_tag" : {
        "type" : "literal",
        "value" : "coworking"
      },
      "itemLabel" : {
        "xml:lang" : "de",
        "type" : "literal",
        "value" : "Co-working (Zusammenarbeit in \"freien Berufen\")"
      }
    }, {
      "item" : {
        "type" : "uri",
        "value" : "http://base.transformap.co/entity/Q115"
      },
      "subclass_of" : {
        "type" : "uri",
        "value" : "http://base.transformap.co/entity/Q15"
      },
      "instance_of" : {
        "type" : "uri",
        "value" : "http://base.transformap.co/entity/Q6"
      },
      "type_of_initiative_tag" : {
        "type" : "literal",
        "value" : "business_incubators"
      },
      "itemLabel" : {
        "xml:lang" : "de",
        "type" : "literal",
        "value" : "UnternehmerInnen- und GründerInnenzentren"
      }
    }, {
      "item" : {
        "type" : "uri",
        "value" : "http://base.transformap.co/entity/Q116"
      },
      "subclass_of" : {
        "type" : "uri",
        "value" : "http://base.transformap.co/entity/Q15"
      },
      "instance_of" : {
        "type" : "uri",
        "value" : "http://base.transformap.co/entity/Q6"
      },
      "type_of_initiative_tag" : {
        "type" : "literal",
        "value" : "entrepreneurship_education"
      },
      "itemLabel" : {
        "xml:lang" : "de",
        "type" : "literal",
        "value" : "Entrepreneurship Bildungsmaßnahmen"
      }
    }, {
      "item" : {
        "type" : "uri",
        "value" : "http://base.transformap.co/entity/Q117"
      },
      "subclass_of" : {
        "type" : "uri",
        "value" : "http://base.transformap.co/entity/Q15"
      },
      "instance_of" : {
        "type" : "uri",
        "value" : "http://base.transformap.co/entity/Q6"
      },
      "type_of_initiative_tag" : {
        "type" : "literal",
        "value" : "social_incubators"
      },
      "itemLabel" : {
        "xml:lang" : "de",
        "type" : "literal",
        "value" : "Social business Inkubator"
      }
    }, {
      "item" : {
        "type" : "uri",
        "value" : "http://base.transformap.co/entity/Q118"
      },
      "subclass_of" : {
        "type" : "uri",
        "value" : "http://base.transformap.co/entity/Q15"
      },
      "instance_of" : {
        "type" : "uri",
        "value" : "http://base.transformap.co/entity/Q6"
      },
      "type_of_initiative_tag" : {
        "type" : "literal",
        "value" : "sse_education"
      },
      "itemLabel" : {
        "xml:lang" : "de",
        "type" : "literal",
        "value" : "Bildung zu Nachhaltigkeit und Solidarität"
      }
    }, {
      "item" : {
        "type" : "uri",
        "value" : "http://base.transformap.co/entity/Q119"
      },
      "subclass_of" : {
        "type" : "uri",
        "value" : "http://base.transformap.co/entity/Q15"
      },
      "instance_of" : {
        "type" : "uri",
        "value" : "http://base.transformap.co/entity/Q6"
      },
      "type_of_initiative_tag" : {
        "type" : "literal",
        "value" : "sse_research"
      },
      "itemLabel" : {
        "xml:lang" : "de",
        "type" : "literal",
        "value" : "Forschung zu Nachhaltigkeit und Solidarität"
      }
    }, {
      "item" : {
        "type" : "uri",
        "value" : "http://base.transformap.co/entity/Q12"
      },
      "subclass_of" : {
        "type" : "uri",
        "value" : "http://base.transformap.co/entity/Q8"
      },
      "instance_of" : {
        "type" : "uri",
        "value" : "http://base.transformap.co/entity/Q5"
      },
      "itemLabel" : {
        "xml:lang" : "de",
        "type" : "literal",
        "value" : "Wohnen und Lebensraum"
      }
    }, {
      "item" : {
        "type" : "uri",
        "value" : "http://base.transformap.co/entity/Q120"
      },
      "subclass_of" : {
        "type" : "uri",
        "value" : "http://base.transformap.co/entity/Q15"
      },
      "instance_of" : {
        "type" : "uri",
        "value" : "http://base.transformap.co/entity/Q6"
      },
      "type_of_initiative_tag" : {
        "type" : "literal",
        "value" : "other_education"
      },
      "itemLabel" : {
        "xml:lang" : "de",
        "type" : "literal",
        "value" : "Andere (Bildungsprojekte etc.)"
      }
    }, {
      "item" : {
        "type" : "uri",
        "value" : "http://base.transformap.co/entity/Q121"
      },
      "subclass_of" : {
        "type" : "uri",
        "value" : "http://base.transformap.co/entity/Q16"
      },
      "instance_of" : {
        "type" : "uri",
        "value" : "http://base.transformap.co/entity/Q6"
      },
      "type_of_initiative_tag" : {
        "type" : "literal",
        "value" : "communitycurrency"
      },
      "itemLabel" : {
        "xml:lang" : "de",
        "type" : "literal",
        "value" : "Regionalwährung"
      }
    }, {
      "item" : {
        "type" : "uri",
        "value" : "http://base.transformap.co/entity/Q122"
      },
      "subclass_of" : {
        "type" : "uri",
        "value" : "http://base.transformap.co/entity/Q16"
      },
      "instance_of" : {
        "type" : "uri",
        "value" : "http://base.transformap.co/entity/Q6"
      },
      "type_of_initiative_tag" : {
        "type" : "literal",
        "value" : "microfinance"
      },
      "itemLabel" : {
        "xml:lang" : "de",
        "type" : "literal",
        "value" : "Mikrokredite"
      }
    }, {
      "item" : {
        "type" : "uri",
        "value" : "http://base.transformap.co/entity/Q123"
      },
      "subclass_of" : {
        "type" : "uri",
        "value" : "http://base.transformap.co/entity/Q16"
      },
      "instance_of" : {
        "type" : "uri",
        "value" : "http://base.transformap.co/entity/Q6"
      },
      "type_of_initiative_tag" : {
        "type" : "literal",
        "value" : "mutual_insurance"
      },
      "itemLabel" : {
        "xml:lang" : "de",
        "type" : "literal",
        "value" : "Gegenseitig-alternative Versicherungsmodelle"
      }
    }, {
      "item" : {
        "type" : "uri",
        "value" : "http://base.transformap.co/entity/Q123"
      },
      "subclass_of" : {
        "type" : "uri",
        "value" : "http://base.transformap.co/entity/Q18"
      },
      "instance_of" : {
        "type" : "uri",
        "value" : "http://base.transformap.co/entity/Q6"
      },
      "type_of_initiative_tag" : {
        "type" : "literal",
        "value" : "mutual_insurance"
      },
      "itemLabel" : {
        "xml:lang" : "de",
        "type" : "literal",
        "value" : "Gegenseitig-alternative Versicherungsmodelle"
      }
    }, {
      "item" : {
        "type" : "uri",
        "value" : "http://base.transformap.co/entity/Q124"
      },
      "subclass_of" : {
        "type" : "uri",
        "value" : "http://base.transformap.co/entity/Q16"
      },
      "instance_of" : {
        "type" : "uri",
        "value" : "http://base.transformap.co/entity/Q6"
      },
      "type_of_initiative_tag" : {
        "type" : "literal",
        "value" : "ethicalfinance_education"
      },
      "itemLabel" : {
        "xml:lang" : "de",
        "type" : "literal",
        "value" : "Förderung ethischer Finanzierungsmodelle"
      }
    }, {
      "item" : {
        "type" : "uri",
        "value" : "http://base.transformap.co/entity/Q125"
      },
      "subclass_of" : {
        "type" : "uri",
        "value" : "http://base.transformap.co/entity/Q16"
      },
      "instance_of" : {
        "type" : "uri",
        "value" : "http://base.transformap.co/entity/Q6"
      },
      "type_of_initiative_tag" : {
        "type" : "literal",
        "value" : "solidarity_lending"
      },
      "itemLabel" : {
        "xml:lang" : "de",
        "type" : "literal",
        "value" : "Solidarische Leihsysteme"
      }
    }, {
      "item" : {
        "type" : "uri",
        "value" : "http://base.transformap.co/entity/Q126"
      },
      "subclass_of" : {
        "type" : "uri",
        "value" : "http://base.transformap.co/entity/Q16"
      },
      "instance_of" : {
        "type" : "uri",
        "value" : "http://base.transformap.co/entity/Q6"
      },
      "type_of_initiative_tag" : {
        "type" : "literal",
        "value" : "timebanking"
      },
      "itemLabel" : {
        "xml:lang" : "de",
        "type" : "literal",
        "value" : "Tauschkreise"
      }
    }, {
      "item" : {
        "type" : "uri",
        "value" : "http://base.transformap.co/entity/Q127"
      },
      "subclass_of" : {
        "type" : "uri",
        "value" : "http://base.transformap.co/entity/Q16"
      },
      "instance_of" : {
        "type" : "uri",
        "value" : "http://base.transformap.co/entity/Q6"
      },
      "type_of_initiative_tag" : {
        "type" : "literal",
        "value" : "other_finance"
      },
      "itemLabel" : {
        "xml:lang" : "de",
        "type" : "literal",
        "value" : "Andere (Finanzen, Tausch, Geld)"
      }
    }, {
      "item" : {
        "type" : "uri",
        "value" : "http://base.transformap.co/entity/Q13"
      },
      "subclass_of" : {
        "type" : "uri",
        "value" : "http://base.transformap.co/entity/Q8"
      },
      "instance_of" : {
        "type" : "uri",
        "value" : "http://base.transformap.co/entity/Q5"
      },
      "itemLabel" : {
        "xml:lang" : "de",
        "type" : "literal",
        "value" : "Infrastruktur und Ressourcen"
      }
    }, {
      "item" : {
        "type" : "uri",
        "value" : "http://base.transformap.co/entity/Q139"
      },
      "subclass_of" : {
        "type" : "uri",
        "value" : "http://base.transformap.co/entity/Q18"
      },
      "instance_of" : {
        "type" : "uri",
        "value" : "http://base.transformap.co/entity/Q6"
      },
      "type_of_initiative_tag" : {
        "type" : "literal",
        "value" : "mutualsociety_art"
      },
      "itemLabel" : {
        "xml:lang" : "de",
        "type" : "literal",
        "value" : "Gesellschaft und Kunst"
      }
    }, {
      "item" : {
        "type" : "uri",
        "value" : "http://base.transformap.co/entity/Q14"
      },
      "subclass_of" : {
        "type" : "uri",
        "value" : "http://base.transformap.co/entity/Q8"
      },
      "instance_of" : {
        "type" : "uri",
        "value" : "http://base.transformap.co/entity/Q5"
      },
      "itemLabel" : {
        "xml:lang" : "de",
        "type" : "literal",
        "value" : "Soziale Inklusion"
      }
    }, {
      "item" : {
        "type" : "uri",
        "value" : "http://base.transformap.co/entity/Q140"
      },
      "subclass_of" : {
        "type" : "uri",
        "value" : "http://base.transformap.co/entity/Q18"
      },
      "instance_of" : {
        "type" : "uri",
        "value" : "http://base.transformap.co/entity/Q6"
      },
      "type_of_initiative_tag" : {
        "type" : "literal",
        "value" : "mutualsociety_aid"
      },
      "itemLabel" : {
        "xml:lang" : "de",
        "type" : "literal",
        "value" : "Gesellschaft für gegenseitige Hilfe"
      }
    }, {
      "item" : {
        "type" : "uri",
        "value" : "http://base.transformap.co/entity/Q142"
      },
      "subclass_of" : {
        "type" : "uri",
        "value" : "http://base.transformap.co/entity/Q18"
      },
      "instance_of" : {
        "type" : "uri",
        "value" : "http://base.transformap.co/entity/Q6"
      },
      "type_of_initiative_tag" : {
        "type" : "literal",
        "value" : "other_mutualsociety"
      },
      "itemLabel" : {
        "xml:lang" : "de",
        "type" : "literal",
        "value" : "Andere (Gemeinschaftlichkeit und gegenseitige Hilfe)"
      }
    }, {
      "item" : {
        "type" : "uri",
        "value" : "http://base.transformap.co/entity/Q143"
      },
      "subclass_of" : {
        "type" : "uri",
        "value" : "http://base.transformap.co/entity/Q19"
      },
      "instance_of" : {
        "type" : "uri",
        "value" : "http://base.transformap.co/entity/Q6"
      },
      "type_of_initiative_tag" : {
        "type" : "literal",
        "value" : "ssedas_partneri"
      },
      "itemLabel" : {
        "xml:lang" : "de",
        "type" : "literal",
        "value" : "SSEDAS Partnerorganisationen"
      }
    }, {
      "item" : {
        "type" : "uri",
        "value" : "http://base.transformap.co/entity/Q15"
      },
      "subclass_of" : {
        "type" : "uri",
        "value" : "http://base.transformap.co/entity/Q8"
      },
      "instance_of" : {
        "type" : "uri",
        "value" : "http://base.transformap.co/entity/Q5"
      },
      "itemLabel" : {
        "xml:lang" : "de",
        "type" : "literal",
        "value" : "Bildung und Training"
      }
    }, {
      "item" : {
        "type" : "uri",
        "value" : "http://base.transformap.co/entity/Q16"
      },
      "subclass_of" : {
        "type" : "uri",
        "value" : "http://base.transformap.co/entity/Q8"
      },
      "instance_of" : {
        "type" : "uri",
        "value" : "http://base.transformap.co/entity/Q5"
      },
      "itemLabel" : {
        "xml:lang" : "de",
        "type" : "literal",
        "value" : "Finanzen"
      }
    }, {
      "item" : {
        "type" : "uri",
        "value" : "http://base.transformap.co/entity/Q17"
      },
      "subclass_of" : {
        "type" : "uri",
        "value" : "http://base.transformap.co/entity/Q8"
      },
      "instance_of" : {
        "type" : "uri",
        "value" : "http://base.transformap.co/entity/Q5"
      },
      "itemLabel" : {
        "xml:lang" : "de",
        "type" : "literal",
        "value" : "Aktives BürgerInnen-Engagement"
      }
    }, {
      "item" : {
        "type" : "uri",
        "value" : "http://base.transformap.co/entity/Q18"
      },
      "subclass_of" : {
        "type" : "uri",
        "value" : "http://base.transformap.co/entity/Q8"
      },
      "instance_of" : {
        "type" : "uri",
        "value" : "http://base.transformap.co/entity/Q5"
      },
      "itemLabel" : {
        "xml:lang" : "de",
        "type" : "literal",
        "value" : "Selbstorganisation und Gegenseitigkeit"
      }
    }, {
      "item" : {
        "type" : "uri",
        "value" : "http://base.transformap.co/entity/Q19"
      },
      "subclass_of" : {
        "type" : "uri",
        "value" : "http://base.transformap.co/entity/Q8"
      },
      "instance_of" : {
        "type" : "uri",
        "value" : "http://base.transformap.co/entity/Q5"
      },
      "itemLabel" : {
        "xml:lang" : "de",
        "type" : "literal",
        "value" : "SUSY-Map PartnerInnennetzwerk"
      }
    }, {
      "item" : {
        "type" : "uri",
        "value" : "http://base.transformap.co/entity/Q20"
      },
      "subclass_of" : {
        "type" : "uri",
        "value" : "http://base.transformap.co/entity/Q8"
      },
      "instance_of" : {
        "type" : "uri",
        "value" : "http://base.transformap.co/entity/Q5"
      },
      "itemLabel" : {
        "xml:lang" : "de",
        "type" : "literal",
        "value" : "Andere (Initiativen, Projekte)"
      }
    }, {
      "item" : {
        "type" : "uri",
        "value" : "http://base.transformap.co/entity/Q21"
      },
      "subclass_of" : {
        "type" : "uri",
        "value" : "http://base.transformap.co/entity/Q9"
      },
      "instance_of" : {
        "type" : "uri",
        "value" : "http://base.transformap.co/entity/Q5"
      },
      "itemLabel" : {
        "xml:lang" : "de",
        "type" : "literal",
        "value" : "Selbst- und/oder gemeinschaftlich Pflanzen"
      }
    }, {
      "item" : {
        "type" : "uri",
        "value" : "http://base.transformap.co/entity/Q22"
      },
      "subclass_of" : {
        "type" : "uri",
        "value" : "http://base.transformap.co/entity/Q21"
      },
      "instance_of" : {
        "type" : "uri",
        "value" : "http://base.transformap.co/entity/Q6"
      },
      "type_of_initiative_tag" : {
        "type" : "literal",
        "value" : "community_garden"
      },
      "itemLabel" : {
        "xml:lang" : "de",
        "type" : "literal",
        "value" : "Gemeinschaftsgarten"
      }
    }, {
      "item" : {
        "type" : "uri",
        "value" : "http://base.transformap.co/entity/Q24"
      },
      "subclass_of" : {
        "type" : "uri",
        "value" : "http://base.transformap.co/entity/Q9"
      },
      "instance_of" : {
        "type" : "uri",
        "value" : "http://base.transformap.co/entity/Q6"
      },
      "type_of_initiative_tag" : {
        "type" : "literal",
        "value" : "edible_town"
      },
      "itemLabel" : {
        "xml:lang" : "de",
        "type" : "literal",
        "value" : "Essbare Gemeinde/Stadt"
      }
    }, {
      "item" : {
        "type" : "uri",
        "value" : "http://base.transformap.co/entity/Q25"
      },
      "subclass_of" : {
        "type" : "uri",
        "value" : "http://base.transformap.co/entity/Q26"
      },
      "instance_of" : {
        "type" : "uri",
        "value" : "http://base.transformap.co/entity/Q6"
      },
      "type_of_initiative_tag" : {
        "type" : "literal",
        "value" : "communitysupported_agriculture"
      },
      "itemLabel" : {
        "xml:lang" : "de",
        "type" : "literal",
        "value" : "Solidarische Landwirtschaft"
      }
    }, {
      "item" : {
        "type" : "uri",
        "value" : "http://base.transformap.co/entity/Q25"
      },
      "subclass_of" : {
        "type" : "uri",
        "value" : "http://base.transformap.co/entity/Q9"
      },
      "instance_of" : {
        "type" : "uri",
        "value" : "http://base.transformap.co/entity/Q6"
      },
      "type_of_initiative_tag" : {
        "type" : "literal",
        "value" : "communitysupported_agriculture"
      },
      "itemLabel" : {
        "xml:lang" : "de",
        "type" : "literal",
        "value" : "Solidarische Landwirtschaft"
      }
    }, {
      "item" : {
        "type" : "uri",
        "value" : "http://base.transformap.co/entity/Q26"
      },
      "subclass_of" : {
        "type" : "uri",
        "value" : "http://base.transformap.co/entity/Q9"
      },
      "instance_of" : {
        "type" : "uri",
        "value" : "http://base.transformap.co/entity/Q5"
      },
      "itemLabel" : {
        "xml:lang" : "de",
        "type" : "literal",
        "value" : "Lokal kaufen"
      }
    }, {
      "item" : {
        "type" : "uri",
        "value" : "http://base.transformap.co/entity/Q27"
      },
      "subclass_of" : {
        "type" : "uri",
        "value" : "http://base.transformap.co/entity/Q9"
      },
      "instance_of" : {
        "type" : "uri",
        "value" : "http://base.transformap.co/entity/Q5"
      },
      "itemLabel" : {
        "xml:lang" : "de",
        "type" : "literal",
        "value" : "Lebensmittel-Rettung"
      }
    }, {
      "item" : {
        "type" : "uri",
        "value" : "http://base.transformap.co/entity/Q28"
      },
      "subclass_of" : {
        "type" : "uri",
        "value" : "http://base.transformap.co/entity/Q9"
      },
      "instance_of" : {
        "type" : "uri",
        "value" : "http://base.transformap.co/entity/Q5"
      },
      "itemLabel" : {
        "xml:lang" : "de",
        "type" : "literal",
        "value" : "Bildung & Politik"
      }
    }, {
      "item" : {
        "type" : "uri",
        "value" : "http://base.transformap.co/entity/Q29"
      },
      "subclass_of" : {
        "type" : "uri",
        "value" : "http://base.transformap.co/entity/Q11"
      },
      "instance_of" : {
        "type" : "uri",
        "value" : "http://base.transformap.co/entity/Q5"
      },
      "itemLabel" : {
        "xml:lang" : "de",
        "type" : "literal",
        "value" : "Reduzieren"
      }
    }, {
      "item" : {
        "type" : "uri",
        "value" : "http://base.transformap.co/entity/Q30"
      },
      "subclass_of" : {
        "type" : "uri",
        "value" : "http://base.transformap.co/entity/Q11"
      },
      "instance_of" : {
        "type" : "uri",
        "value" : "http://base.transformap.co/entity/Q5"
      },
      "itemLabel" : {
        "xml:lang" : "de",
        "type" : "literal",
        "value" : "Teilen und Wiederverwenden"
      }
    }, {
      "item" : {
        "type" : "uri",
        "value" : "http://base.transformap.co/entity/Q31"
      },
      "subclass_of" : {
        "type" : "uri",
        "value" : "http://base.transformap.co/entity/Q11"
      },
      "instance_of" : {
        "type" : "uri",
        "value" : "http://base.transformap.co/entity/Q5"
      },
      "itemLabel" : {
        "xml:lang" : "de",
        "type" : "literal",
        "value" : "Reparieren"
      }
    }, {
      "item" : {
        "type" : "uri",
        "value" : "http://base.transformap.co/entity/Q32"
      },
      "subclass_of" : {
        "type" : "uri",
        "value" : "http://base.transformap.co/entity/Q11"
      },
      "instance_of" : {
        "type" : "uri",
        "value" : "http://base.transformap.co/entity/Q5"
      },
      "itemLabel" : {
        "xml:lang" : "de",
        "type" : "literal",
        "value" : "Recycling & Upcycling"
      }
    }, {
      "item" : {
        "type" : "uri",
        "value" : "http://base.transformap.co/entity/Q33"
      },
      "subclass_of" : {
        "type" : "uri",
        "value" : "http://base.transformap.co/entity/Q17"
      },
      "instance_of" : {
        "type" : "uri",
        "value" : "http://base.transformap.co/entity/Q5"
      },
      "itemLabel" : {
        "xml:lang" : "de",
        "type" : "literal",
        "value" : "Politisches Engagement"
      }
    }, {
      "item" : {
        "type" : "uri",
        "value" : "http://base.transformap.co/entity/Q34"
      },
      "subclass_of" : {
        "type" : "uri",
        "value" : "http://base.transformap.co/entity/Q17"
      },
      "instance_of" : {
        "type" : "uri",
        "value" : "http://base.transformap.co/entity/Q5"
      },
      "itemLabel" : {
        "xml:lang" : "de",
        "type" : "literal",
        "value" : "Partizipation"
      }
    }, {
      "item" : {
        "type" : "uri",
        "value" : "http://base.transformap.co/entity/Q35"
      },
      "subclass_of" : {
        "type" : "uri",
        "value" : "http://base.transformap.co/entity/Q17"
      },
      "instance_of" : {
        "type" : "uri",
        "value" : "http://base.transformap.co/entity/Q5"
      },
      "itemLabel" : {
        "xml:lang" : "de",
        "type" : "literal",
        "value" : "Gemeindenetzwerk"
      }
    }, {
      "item" : {
        "type" : "uri",
        "value" : "http://base.transformap.co/entity/Q36"
      },
      "subclass_of" : {
        "type" : "uri",
        "value" : "http://base.transformap.co/entity/Q21"
      },
      "instance_of" : {
        "type" : "uri",
        "value" : "http://base.transformap.co/entity/Q6"
      },
      "type_of_initiative_tag" : {
        "type" : "literal",
        "value" : "foodpurchasing_combine"
      },
      "itemLabel" : {
        "xml:lang" : "de",
        "type" : "literal",
        "value" : "Foodcoop"
      }
    }, {
      "item" : {
        "type" : "uri",
        "value" : "http://base.transformap.co/entity/Q36"
      },
      "subclass_of" : {
        "type" : "uri",
        "value" : "http://base.transformap.co/entity/Q26"
      },
      "instance_of" : {
        "type" : "uri",
        "value" : "http://base.transformap.co/entity/Q6"
      },
      "type_of_initiative_tag" : {
        "type" : "literal",
        "value" : "foodpurchasing_combine"
      },
      "itemLabel" : {
        "xml:lang" : "de",
        "type" : "literal",
        "value" : "Foodcoop"
      }
    }, {
      "item" : {
        "type" : "uri",
        "value" : "http://base.transformap.co/entity/Q37"
      },
      "subclass_of" : {
        "type" : "uri",
        "value" : "http://base.transformap.co/entity/Q21"
      },
      "instance_of" : {
        "type" : "uri",
        "value" : "http://base.transformap.co/entity/Q6"
      },
      "type_of_initiative_tag" : {
        "type" : "literal",
        "value" : "guerilla_garden"
      },
      "itemLabel" : {
        "xml:lang" : "de",
        "type" : "literal",
        "value" : "Guerilla Gardening"
      }
    }, {
      "item" : {
        "type" : "uri",
        "value" : "http://base.transformap.co/entity/Q38"
      },
      "subclass_of" : {
        "type" : "uri",
        "value" : "http://base.transformap.co/entity/Q21"
      },
      "instance_of" : {
        "type" : "uri",
        "value" : "http://base.transformap.co/entity/Q6"
      },
      "type_of_initiative_tag" : {
        "type" : "literal",
        "value" : "seed_saving"
      },
      "itemLabel" : {
        "xml:lang" : "de",
        "type" : "literal",
        "value" : "Saatgut Initiative"
      }
    }, {
      "item" : {
        "type" : "uri",
        "value" : "http://base.transformap.co/entity/Q38"
      },
      "subclass_of" : {
        "type" : "uri",
        "value" : "http://base.transformap.co/entity/Q28"
      },
      "instance_of" : {
        "type" : "uri",
        "value" : "http://base.transformap.co/entity/Q6"
      },
      "type_of_initiative_tag" : {
        "type" : "literal",
        "value" : "seed_saving"
      },
      "itemLabel" : {
        "xml:lang" : "de",
        "type" : "literal",
        "value" : "Saatgut Initiative"
      }
    }, {
      "item" : {
        "type" : "uri",
        "value" : "http://base.transformap.co/entity/Q39"
      },
      "subclass_of" : {
        "type" : "uri",
        "value" : "http://base.transformap.co/entity/Q21"
      },
      "instance_of" : {
        "type" : "uri",
        "value" : "http://base.transformap.co/entity/Q6"
      },
      "type_of_initiative_tag" : {
        "type" : "literal",
        "value" : "Samostalna berba"
      },
      "itemLabel" : {
        "xml:lang" : "de",
        "type" : "literal",
        "value" : "Selber Pflücken/Ernten"
      }
    }, {
      "item" : {
        "type" : "uri",
        "value" : "http://base.transformap.co/entity/Q40"
      },
      "subclass_of" : {
        "type" : "uri",
        "value" : "http://base.transformap.co/entity/Q21"
      },
      "instance_of" : {
        "type" : "uri",
        "value" : "http://base.transformap.co/entity/Q6"
      },
      "type_of_initiative_tag" : {
        "type" : "literal",
        "value" : "other_growyourself"
      },
      "itemLabel" : {
        "xml:lang" : "de",
        "type" : "literal",
        "value" : "Andere (Zusammen pflanzen, ernten, säen etc.)"
      }
    }, {
      "item" : {
        "type" : "uri",
        "value" : "http://base.transformap.co/entity/Q41"
      },
      "subclass_of" : {
        "type" : "uri",
        "value" : "http://base.transformap.co/entity/Q26"
      },
      "instance_of" : {
        "type" : "uri",
        "value" : "http://base.transformap.co/entity/Q6"
      },
      "type_of_initiative_tag" : {
        "type" : "literal",
        "value" : "farm_shop"
      },
      "itemLabel" : {
        "xml:lang" : "de",
        "type" : "literal",
        "value" : "Ab-Hof Verkauf"
      }
    }, {
      "item" : {
        "type" : "uri",
        "value" : "http://base.transformap.co/entity/Q44"
      },
      "subclass_of" : {
        "type" : "uri",
        "value" : "http://base.transformap.co/entity/Q26"
      },
      "instance_of" : {
        "type" : "uri",
        "value" : "http://base.transformap.co/entity/Q6"
      },
      "type_of_initiative_tag" : {
        "type" : "literal",
        "value" : "local_farmersmarket"
      },
      "itemLabel" : {
        "xml:lang" : "de",
        "type" : "literal",
        "value" : "Lokaler Bauernmarkt"
      }
    }, {
      "item" : {
        "type" : "uri",
        "value" : "http://base.transformap.co/entity/Q45"
      },
      "subclass_of" : {
        "type" : "uri",
        "value" : "http://base.transformap.co/entity/Q26"
      },
      "instance_of" : {
        "type" : "uri",
        "value" : "http://base.transformap.co/entity/Q6"
      },
      "type_of_initiative_tag" : {
        "type" : "literal",
        "value" : "vegetable_box"
      },
      "itemLabel" : {
        "xml:lang" : "de",
        "type" : "literal",
        "value" : "Bio-Kiste"
      }
    }, {
      "item" : {
        "type" : "uri",
        "value" : "http://base.transformap.co/entity/Q47"
      },
      "subclass_of" : {
        "type" : "uri",
        "value" : "http://base.transformap.co/entity/Q26"
      },
      "instance_of" : {
        "type" : "uri",
        "value" : "http://base.transformap.co/entity/Q6"
      },
      "type_of_initiative_tag" : {
        "type" : "literal",
        "value" : "virtual_directpurchase"
      },
      "itemLabel" : {
        "xml:lang" : "de",
        "type" : "literal",
        "value" : "Virtueller Direkteinkauf"
      }
    }, {
      "item" : {
        "type" : "uri",
        "value" : "http://base.transformap.co/entity/Q48"
      },
      "subclass_of" : {
        "type" : "uri",
        "value" : "http://base.transformap.co/entity/Q26"
      },
      "instance_of" : {
        "type" : "uri",
        "value" : "http://base.transformap.co/entity/Q6"
      },
      "type_of_initiative_tag" : {
        "type" : "literal",
        "value" : "food_cooperative"
      },
      "itemLabel" : {
        "xml:lang" : "de",
        "type" : "literal",
        "value" : "Lebensmittelkooperative"
      }
    }, {
      "item" : {
        "type" : "uri",
        "value" : "http://base.transformap.co/entity/Q49"
      },
      "subclass_of" : {
        "type" : "uri",
        "value" : "http://base.transformap.co/entity/Q26"
      },
      "instance_of" : {
        "type" : "uri",
        "value" : "http://base.transformap.co/entity/Q6"
      },
      "type_of_initiative_tag" : {
        "type" : "literal",
        "value" : "other_buylocal"
      },
      "itemLabel" : {
        "xml:lang" : "de",
        "type" : "literal",
        "value" : "Andere (Lokale Ernährung, Einkauf)"
      }
    }, {
      "item" : {
        "type" : "uri",
        "value" : "http://base.transformap.co/entity/Q50"
      },
      "subclass_of" : {
        "type" : "uri",
        "value" : "http://base.transformap.co/entity/Q10"
      },
      "instance_of" : {
        "type" : "uri",
        "value" : "http://base.transformap.co/entity/Q6"
      },
      "type_of_initiative_tag" : {
        "type" : "literal",
        "value" : "fairtrade_shop"
      },
      "itemLabel" : {
        "xml:lang" : "de",
        "type" : "literal",
        "value" : "Geschäft des Fairen Handels"
      }
    }, {
      "item" : {
        "type" : "uri",
        "value" : "http://base.transformap.co/entity/Q52"
      },
      "subclass_of" : {
        "type" : "uri",
        "value" : "http://base.transformap.co/entity/Q27"
      },
      "instance_of" : {
        "type" : "uri",
        "value" : "http://base.transformap.co/entity/Q6"
      },
      "type_of_initiative_tag" : {
        "type" : "literal",
        "value" : "foodrescue"
      },
      "itemLabel" : {
        "xml:lang" : "de",
        "type" : "literal",
        "value" : "Foodsharing Gruppe"
      }
    }, {
      "item" : {
        "type" : "uri",
        "value" : "http://base.transformap.co/entity/Q53"
      },
      "subclass_of" : {
        "type" : "uri",
        "value" : "http://base.transformap.co/entity/Q27"
      },
      "instance_of" : {
        "type" : "uri",
        "value" : "http://base.transformap.co/entity/Q6"
      },
      "type_of_initiative_tag" : {
        "type" : "literal",
        "value" : "foodrescue_distribution"
      },
      "itemLabel" : {
        "xml:lang" : "de",
        "type" : "literal",
        "value" : "Foodsharing Verteiler"
      }
    }, {
      "item" : {
        "type" : "uri",
        "value" : "http://base.transformap.co/entity/Q54"
      },
      "subclass_of" : {
        "type" : "uri",
        "value" : "http://base.transformap.co/entity/Q27"
      },
      "instance_of" : {
        "type" : "uri",
        "value" : "http://base.transformap.co/entity/Q6"
      },
      "type_of_initiative_tag" : {
        "type" : "literal",
        "value" : "foodrescue_cuisine"
      },
      "itemLabel" : {
        "xml:lang" : "de",
        "type" : "literal",
        "value" : "Essensrettungsküche"
      }
    }, {
      "item" : {
        "type" : "uri",
        "value" : "http://base.transformap.co/entity/Q55"
      },
      "subclass_of" : {
        "type" : "uri",
        "value" : "http://base.transformap.co/entity/Q27"
      },
      "instance_of" : {
        "type" : "uri",
        "value" : "http://base.transformap.co/entity/Q6"
      },
      "type_of_initiative_tag" : {
        "type" : "literal",
        "value" : "recycling_foodwaste"
      },
      "itemLabel" : {
        "xml:lang" : "de",
        "type" : "literal",
        "value" : "Verwertung von Nahrungsmittelresten"
      }
    }, {
      "item" : {
        "type" : "uri",
        "value" : "http://base.transformap.co/entity/Q56"
      },
      "subclass_of" : {
        "type" : "uri",
        "value" : "http://base.transformap.co/entity/Q27"
      },
      "instance_of" : {
        "type" : "uri",
        "value" : "http://base.transformap.co/entity/Q6"
      },
      "type_of_initiative_tag" : {
        "type" : "literal",
        "value" : "other_foodrescue"
      },
      "itemLabel" : {
        "xml:lang" : "de",
        "type" : "literal",
        "value" : "Andere (Essensrettung, Essen)"
      }
    }, {
      "item" : {
        "type" : "uri",
        "value" : "http://base.transformap.co/entity/Q57"
      },
      "subclass_of" : {
        "type" : "uri",
        "value" : "http://base.transformap.co/entity/Q28"
      },
      "instance_of" : {
        "type" : "uri",
        "value" : "http://base.transformap.co/entity/Q6"
      },
      "type_of_initiative_tag" : {
        "type" : "literal",
        "value" : "agro_empowerment"
      },
      "itemLabel" : {
        "xml:lang" : "de",
        "type" : "literal",
        "value" : "Stärkung kleinbäuerlicher Landwirtschaft"
      }
    }, {
      "item" : {
        "type" : "uri",
        "value" : "http://base.transformap.co/entity/Q58"
      },
      "subclass_of" : {
        "type" : "uri",
        "value" : "http://base.transformap.co/entity/Q28"
      },
      "instance_of" : {
        "type" : "uri",
        "value" : "http://base.transformap.co/entity/Q6"
      },
      "type_of_initiative_tag" : {
        "type" : "literal",
        "value" : "agroecology_education"
      },
      "itemLabel" : {
        "xml:lang" : "de",
        "type" : "literal",
        "value" : "Landwirtschaftlich-ökologische Bildung"
      }
    }, {
      "item" : {
        "type" : "uri",
        "value" : "http://base.transformap.co/entity/Q59"
      },
      "subclass_of" : {
        "type" : "uri",
        "value" : "http://base.transformap.co/entity/Q28"
      },
      "instance_of" : {
        "type" : "uri",
        "value" : "http://base.transformap.co/entity/Q6"
      },
      "type_of_initiative_tag" : {
        "type" : "literal",
        "value" : "agro_sucessionnetwork"
      },
      "itemLabel" : {
        "xml:lang" : "de",
        "type" : "literal",
        "value" : "Hofübergabe Netzwerk"
      }
    }, {
      "item" : {
        "type" : "uri",
        "value" : "http://base.transformap.co/entity/Q60"
      },
      "subclass_of" : {
        "type" : "uri",
        "value" : "http://base.transformap.co/entity/Q28"
      },
      "instance_of" : {
        "type" : "uri",
        "value" : "http://base.transformap.co/entity/Q6"
      },
      "type_of_initiative_tag" : {
        "type" : "literal",
        "value" : "foodpolicy_council"
      },
      "itemLabel" : {
        "xml:lang" : "de",
        "type" : "literal",
        "value" : "Ernährungsrat"
      }
    }, {
      "item" : {
        "type" : "uri",
        "value" : "http://base.transformap.co/entity/Q61"
      },
      "subclass_of" : {
        "type" : "uri",
        "value" : "http://base.transformap.co/entity/Q28"
      },
      "instance_of" : {
        "type" : "uri",
        "value" : "http://base.transformap.co/entity/Q6"
      },
      "type_of_initiative_tag" : {
        "type" : "literal",
        "value" : "food_souvereignity"
      },
      "itemLabel" : {
        "xml:lang" : "de",
        "type" : "literal",
        "value" : "Ernährungssouveränitäts-Initiative"
      }
    }, {
      "item" : {
        "type" : "uri",
        "value" : "http://base.transformap.co/entity/Q62"
      },
      "subclass_of" : {
        "type" : "uri",
        "value" : "http://base.transformap.co/entity/Q28"
      },
      "instance_of" : {
        "type" : "uri",
        "value" : "http://base.transformap.co/entity/Q6"
      },
      "type_of_initiative_tag" : {
        "type" : "literal",
        "value" : "permaculture_education"
      },
      "itemLabel" : {
        "xml:lang" : "de",
        "type" : "literal",
        "value" : "Permakultur-Bildung"
      }
    }, {
      "item" : {
        "type" : "uri",
        "value" : "http://base.transformap.co/entity/Q63"
      },
      "subclass_of" : {
        "type" : "uri",
        "value" : "http://base.transformap.co/entity/Q28"
      },
      "instance_of" : {
        "type" : "uri",
        "value" : "http://base.transformap.co/entity/Q6"
      },
      "type_of_initiative_tag" : {
        "type" : "literal",
        "value" : "schoolgarden"
      },
      "itemLabel" : {
        "xml:lang" : "de",
        "type" : "literal",
        "value" : "Schulgarten"
      }
    }, {
      "item" : {
        "type" : "uri",
        "value" : "http://base.transformap.co/entity/Q65"
      },
      "subclass_of" : {
        "type" : "uri",
        "value" : "http://base.transformap.co/entity/Q28"
      },
      "instance_of" : {
        "type" : "uri",
        "value" : "http://base.transformap.co/entity/Q6"
      },
      "type_of_initiative_tag" : {
        "type" : "literal",
        "value" : "slowfood"
      },
      "itemLabel" : {
        "xml:lang" : "de",
        "type" : "literal",
        "value" : "Slowfood"
      }
    }, {
      "item" : {
        "type" : "uri",
        "value" : "http://base.transformap.co/entity/Q66"
      },
      "subclass_of" : {
        "type" : "uri",
        "value" : "http://base.transformap.co/entity/Q28"
      },
      "instance_of" : {
        "type" : "uri",
        "value" : "http://base.transformap.co/entity/Q6"
      },
      "type_of_initiative_tag" : {
        "type" : "literal",
        "value" : "other_foodedunpolicy"
      },
      "itemLabel" : {
        "xml:lang" : "de",
        "type" : "literal",
        "value" : "Andere (Ernährungspolitik, Bildungsprojekte, Essen)"
      }
    }, {
      "item" : {
        "type" : "uri",
        "value" : "http://base.transformap.co/entity/Q68"
      },
      "subclass_of" : {
        "type" : "uri",
        "value" : "http://base.transformap.co/entity/Q10"
      },
      "instance_of" : {
        "type" : "uri",
        "value" : "http://base.transformap.co/entity/Q6"
      },
      "type_of_initiative_tag" : {
        "type" : "literal",
        "value" : "fairtrade_school"
      },
      "itemLabel" : {
        "xml:lang" : "de",
        "type" : "literal",
        "value" : "Fairtrade Schule"
      }
    }, {
      "item" : {
        "type" : "uri",
        "value" : "http://base.transformap.co/entity/Q69"
      },
      "subclass_of" : {
        "type" : "uri",
        "value" : "http://base.transformap.co/entity/Q10"
      },
      "type_of_initiative_tag" : {
        "type" : "literal",
        "value" : "fairtrade_town"
      },
      "itemLabel" : {
        "xml:lang" : "de",
        "type" : "literal",
        "value" : "Fairtrade Gemeinde"
      }
    }, {
      "item" : {
        "type" : "uri",
        "value" : "http://base.transformap.co/entity/Q70"
      },
      "subclass_of" : {
        "type" : "uri",
        "value" : "http://base.transformap.co/entity/Q10"
      },
      "instance_of" : {
        "type" : "uri",
        "value" : "http://base.transformap.co/entity/Q6"
      },
      "type_of_initiative_tag" : {
        "type" : "literal",
        "value" : "fairtrade_wholesaler"
      },
      "itemLabel" : {
        "xml:lang" : "de",
        "type" : "literal",
        "value" : "Fairer Handel (Großhandel)"
      }
    }, {
      "item" : {
        "type" : "uri",
        "value" : "http://base.transformap.co/entity/Q71"
      },
      "subclass_of" : {
        "type" : "uri",
        "value" : "http://base.transformap.co/entity/Q10"
      },
      "instance_of" : {
        "type" : "uri",
        "value" : "http://base.transformap.co/entity/Q6"
      },
      "type_of_initiative_tag" : {
        "type" : "literal",
        "value" : "directtrade"
      },
      "itemLabel" : {
        "xml:lang" : "de",
        "type" : "literal",
        "value" : "Direkthandel"
      }
    }, {
      "item" : {
        "type" : "uri",
        "value" : "http://base.transformap.co/entity/Q72"
      },
      "subclass_of" : {
        "type" : "uri",
        "value" : "http://base.transformap.co/entity/Q10"
      },
      "instance_of" : {
        "type" : "uri",
        "value" : "http://base.transformap.co/entity/Q6"
      },
      "type_of_initiative_tag" : {
        "type" : "literal",
        "value" : "development_cooperation"
      },
      "itemLabel" : {
        "xml:lang" : "de",
        "type" : "literal",
        "value" : "Entwicklungszusammenarbeit"
      }
    }, {
      "item" : {
        "type" : "uri",
        "value" : "http://base.transformap.co/entity/Q73"
      },
      "subclass_of" : {
        "type" : "uri",
        "value" : "http://base.transformap.co/entity/Q10"
      },
      "instance_of" : {
        "type" : "uri",
        "value" : "http://base.transformap.co/entity/Q6"
      },
      "type_of_initiative_tag" : {
        "type" : "literal",
        "value" : "other_fairtrade"
      },
      "itemLabel" : {
        "xml:lang" : "de",
        "type" : "literal",
        "value" : "Andere (Initiativen und Projekte des Fairen Handels und der internationalen Kooperation)"
      }
    }, {
      "item" : {
        "type" : "uri",
        "value" : "http://base.transformap.co/entity/Q74"
      },
      "subclass_of" : {
        "type" : "uri",
        "value" : "http://base.transformap.co/entity/Q29"
      },
      "instance_of" : {
        "type" : "uri",
        "value" : "http://base.transformap.co/entity/Q6"
      },
      "type_of_initiative_tag" : {
        "type" : "literal",
        "value" : "waste_awareness"
      },
      "itemLabel" : {
        "xml:lang" : "de",
        "type" : "literal",
        "value" : "Bewusstseinsbildung für Müllvermeidung"
      }
    }, {
      "item" : {
        "type" : "uri",
        "value" : "http://base.transformap.co/entity/Q75"
      },
      "subclass_of" : {
        "type" : "uri",
        "value" : "http://base.transformap.co/entity/Q29"
      },
      "instance_of" : {
        "type" : "uri",
        "value" : "http://base.transformap.co/entity/Q6"
      },
      "type_of_initiative_tag" : {
        "type" : "literal",
        "value" : "nopacking_shop"
      },
      "itemLabel" : {
        "xml:lang" : "de",
        "type" : "literal",
        "value" : "Verpackungsfreie Läden und Initiativen"
      }
    }, {
      "item" : {
        "type" : "uri",
        "value" : "http://base.transformap.co/entity/Q76"
      },
      "subclass_of" : {
        "type" : "uri",
        "value" : "http://base.transformap.co/entity/Q29"
      },
      "instance_of" : {
        "type" : "uri",
        "value" : "http://base.transformap.co/entity/Q6"
      },
      "type_of_initiative_tag" : {
        "type" : "literal",
        "value" : "other_wastereduction"
      },
      "itemLabel" : {
        "xml:lang" : "de",
        "type" : "literal",
        "value" : "Andere (Müllvermeidungsprojekte und -initiativen)"
      }
    }, {
      "item" : {
        "type" : "uri",
        "value" : "http://base.transformap.co/entity/Q77"
      },
      "subclass_of" : {
        "type" : "uri",
        "value" : "http://base.transformap.co/entity/Q30"
      },
      "instance_of" : {
        "type" : "uri",
        "value" : "http://base.transformap.co/entity/Q6"
      },
      "type_of_initiative_tag" : {
        "type" : "literal",
        "value" : "used_goods"
      },
      "itemLabel" : {
        "xml:lang" : "de",
        "type" : "literal",
        "value" : "Gebrauchtwarenhandel"
      }
    }, {
      "item" : {
        "type" : "uri",
        "value" : "http://base.transformap.co/entity/Q9"
      },
      "subclass_of" : {
        "type" : "uri",
        "value" : "http://base.transformap.co/entity/Q8"
      },
      "instance_of" : {
        "type" : "uri",
        "value" : "http://base.transformap.co/entity/Q5"
      },
      "itemLabel" : {
        "xml:lang" : "de",
        "type" : "literal",
        "value" : "Lebensmittel und Landwirtschaft"
      }
    }, {
      "item" : {
        "type" : "uri",
        "value" : "http://base.transformap.co/entity/Q95"
      },
      "subclass_of" : {
        "type" : "uri",
        "value" : "http://base.transformap.co/entity/Q12"
      },
      "instance_of" : {
        "type" : "uri",
        "value" : "http://base.transformap.co/entity/Q6"
      },
      "type_of_initiative_tag" : {
        "type" : "literal",
        "value" : "cohousing"
      },
      "itemLabel" : {
        "xml:lang" : "de",
        "type" : "literal",
        "value" : "Cohousing"
      }
    }, {
      "item" : {
        "type" : "uri",
        "value" : "http://base.transformap.co/entity/Q96"
      },
      "subclass_of" : {
        "type" : "uri",
        "value" : "http://base.transformap.co/entity/Q12"
      },
      "instance_of" : {
        "type" : "uri",
        "value" : "http://base.transformap.co/entity/Q6"
      },
      "type_of_initiative_tag" : {
        "type" : "literal",
        "value" : "commune"
      },
      "itemLabel" : {
        "xml:lang" : "de",
        "type" : "literal",
        "value" : "Kommune"
      }
    }, {
      "item" : {
        "type" : "uri",
        "value" : "http://base.transformap.co/entity/Q97"
      },
      "subclass_of" : {
        "type" : "uri",
        "value" : "http://base.transformap.co/entity/Q12"
      },
      "instance_of" : {
        "type" : "uri",
        "value" : "http://base.transformap.co/entity/Q6"
      },
      "type_of_initiative_tag" : {
        "type" : "literal",
        "value" : "ecovillage"
      },
      "itemLabel" : {
        "xml:lang" : "de",
        "type" : "literal",
        "value" : "Ökodorf"
      }
    }, {
      "item" : {
        "type" : "uri",
        "value" : "http://base.transformap.co/entity/Q98"
      },
      "subclass_of" : {
        "type" : "uri",
        "value" : "http://base.transformap.co/entity/Q12"
      },
      "instance_of" : {
        "type" : "uri",
        "value" : "http://base.transformap.co/entity/Q6"
      },
      "type_of_initiative_tag" : {
        "type" : "literal",
        "value" : "squatted_place"
      },
      "itemLabel" : {
        "xml:lang" : "de",
        "type" : "literal",
        "value" : "Hausbesetzung"
      }
    }, {
      "item" : {
        "type" : "uri",
        "value" : "http://base.transformap.co/entity/Q99"
      },
      "subclass_of" : {
        "type" : "uri",
        "value" : "http://base.transformap.co/entity/Q12"
      },
      "instance_of" : {
        "type" : "uri",
        "value" : "http://base.transformap.co/entity/Q6"
      },
      "type_of_initiative_tag" : {
        "type" : "literal",
        "value" : "other_habitat"
      },
      "itemLabel" : {
        "xml:lang" : "de",
        "type" : "literal",
        "value" : "Andere (Lebens- und Wohnprojekte)"
      }
    }, {
      "item" : {
        "type" : "uri",
        "value" : "http://base.transformap.co/entity/Q128"
      },
      "subclass_of" : {
        "type" : "uri",
        "value" : "http://base.transformap.co/entity/Q33"
      },
      "instance_of" : {
        "type" : "uri",
        "value" : "http://base.transformap.co/entity/Q6"
      },
      "type_of_initiative_tag" : {
        "type" : "literal",
        "value" : "directdemocracy"
      },
      "itemLabel" : {
        "xml:lang" : "de",
        "type" : "literal",
        "value" : "Initiative für direkte Demokratie"
      }
    }, {
      "item" : {
        "type" : "uri",
        "value" : "http://base.transformap.co/entity/Q129"
      },
      "subclass_of" : {
        "type" : "uri",
        "value" : "http://base.transformap.co/entity/Q33"
      },
      "instance_of" : {
        "type" : "uri",
        "value" : "http://base.transformap.co/entity/Q6"
      },
      "type_of_initiative_tag" : {
        "type" : "literal",
        "value" : "consumerism_awareness"
      },
      "itemLabel" : {
        "xml:lang" : "de",
        "type" : "literal",
        "value" : "KonsumentInnen-Bewusstseinsbildung"
      }
    }, {
      "item" : {
        "type" : "uri",
        "value" : "http://base.transformap.co/entity/Q130"
      },
      "subclass_of" : {
        "type" : "uri",
        "value" : "http://base.transformap.co/entity/Q33"
      },
      "instance_of" : {
        "type" : "uri",
        "value" : "http://base.transformap.co/entity/Q6"
      },
      "type_of_initiative_tag" : {
        "type" : "literal",
        "value" : "other_political"
      },
      "itemLabel" : {
        "xml:lang" : "de",
        "type" : "literal",
        "value" : "Andere (Politische Initiativen)"
      }
    }, {
      "item" : {
        "type" : "uri",
        "value" : "http://base.transformap.co/entity/Q131"
      },
      "subclass_of" : {
        "type" : "uri",
        "value" : "http://base.transformap.co/entity/Q34"
      },
      "instance_of" : {
        "type" : "uri",
        "value" : "http://base.transformap.co/entity/Q6"
      },
      "type_of_initiative_tag" : {
        "type" : "literal",
        "value" : "participatory_budgeting"
      },
      "itemLabel" : {
        "xml:lang" : "de",
        "type" : "literal",
        "value" : "Partizipatives Gemeindebudget"
      }
    }, {
      "item" : {
        "type" : "uri",
        "value" : "http://base.transformap.co/entity/Q132"
      },
      "subclass_of" : {
        "type" : "uri",
        "value" : "http://base.transformap.co/entity/Q34"
      },
      "instance_of" : {
        "type" : "uri",
        "value" : "http://base.transformap.co/entity/Q6"
      },
      "type_of_initiative_tag" : {
        "type" : "literal",
        "value" : "citizen_council"
      },
      "itemLabel" : {
        "xml:lang" : "de",
        "type" : "literal",
        "value" : "BürgerInnenrat"
      }
    }, {
      "item" : {
        "type" : "uri",
        "value" : "http://base.transformap.co/entity/Q133"
      },
      "subclass_of" : {
        "type" : "uri",
        "value" : "http://base.transformap.co/entity/Q34"
      },
      "instance_of" : {
        "type" : "uri",
        "value" : "http://base.transformap.co/entity/Q6"
      },
      "type_of_initiative_tag" : {
        "type" : "literal",
        "value" : "youth_council"
      },
      "itemLabel" : {
        "xml:lang" : "de",
        "type" : "literal",
        "value" : "Jugendrat"
      }
    }, {
      "item" : {
        "type" : "uri",
        "value" : "http://base.transformap.co/entity/Q134"
      },
      "subclass_of" : {
        "type" : "uri",
        "value" : "http://base.transformap.co/entity/Q34"
      },
      "instance_of" : {
        "type" : "uri",
        "value" : "http://base.transformap.co/entity/Q6"
      },
      "type_of_initiative_tag" : {
        "type" : "literal",
        "value" : "other_participation"
      },
      "itemLabel" : {
        "xml:lang" : "de",
        "type" : "literal",
        "value" : "Andere (Partizipation, Mitsprache)"
      }
    }, {
      "item" : {
        "type" : "uri",
        "value" : "http://base.transformap.co/entity/Q135"
      },
      "subclass_of" : {
        "type" : "uri",
        "value" : "http://base.transformap.co/entity/Q35"
      },
      "instance_of" : {
        "type" : "uri",
        "value" : "http://base.transformap.co/entity/Q6"
      },
      "type_of_initiative_tag" : {
        "type" : "literal",
        "value" : "ngo"
      },
      "itemLabel" : {
        "xml:lang" : "de",
        "type" : "literal",
        "value" : "NGO"
      }
    }, {
      "item" : {
        "type" : "uri",
        "value" : "http://base.transformap.co/entity/Q136"
      },
      "subclass_of" : {
        "type" : "uri",
        "value" : "http://base.transformap.co/entity/Q35"
      },
      "instance_of" : {
        "type" : "uri",
        "value" : "http://base.transformap.co/entity/Q6"
      },
      "type_of_initiative_tag" : {
        "type" : "literal",
        "value" : "community_group"
      },
      "itemLabel" : {
        "xml:lang" : "de",
        "type" : "literal",
        "value" : "Gemeinschaftsinitiatve"
      }
    }, {
      "item" : {
        "type" : "uri",
        "value" : "http://base.transformap.co/entity/Q137"
      },
      "subclass_of" : {
        "type" : "uri",
        "value" : "http://base.transformap.co/entity/Q35"
      },
      "instance_of" : {
        "type" : "uri",
        "value" : "http://base.transformap.co/entity/Q6"
      },
      "type_of_initiative_tag" : {
        "type" : "literal",
        "value" : "networking_initiative"
      },
      "itemLabel" : {
        "xml:lang" : "de",
        "type" : "literal",
        "value" : "Vernetzungsinitiative"
      }
    }, {
      "item" : {
        "type" : "uri",
        "value" : "http://base.transformap.co/entity/Q138"
      },
      "subclass_of" : {
        "type" : "uri",
        "value" : "http://base.transformap.co/entity/Q35"
      },
      "instance_of" : {
        "type" : "uri",
        "value" : "http://base.transformap.co/entity/Q6"
      },
      "type_of_initiative_tag" : {
        "type" : "literal",
        "value" : "other_communities"
      },
      "itemLabel" : {
        "xml:lang" : "de",
        "type" : "literal",
        "value" : "Andere (Gemeinschaftsprojekte, Vernetzung)"
      }
    }, {
      "item" : {
        "type" : "uri",
        "value" : "http://base.transformap.co/entity/Q78"
      },
      "subclass_of" : {
        "type" : "uri",
        "value" : "http://base.transformap.co/entity/Q30"
      },
      "instance_of" : {
        "type" : "uri",
        "value" : "http://base.transformap.co/entity/Q6"
      },
      "type_of_initiative_tag" : {
        "type" : "literal",
        "value" : "fleamarket"
      },
      "itemLabel" : {
        "xml:lang" : "de",
        "type" : "literal",
        "value" : "Flohmarkt"
      }
    }, {
      "item" : {
        "type" : "uri",
        "value" : "http://base.transformap.co/entity/Q79"
      },
      "subclass_of" : {
        "type" : "uri",
        "value" : "http://base.transformap.co/entity/Q30"
      },
      "instance_of" : {
        "type" : "uri",
        "value" : "http://base.transformap.co/entity/Q6"
      },
      "type_of_initiative_tag" : {
        "type" : "literal",
        "value" : "garment_rental"
      },
      "itemLabel" : {
        "xml:lang" : "de",
        "type" : "literal",
        "value" : "Bekleidungsverleih"
      }
    }, {
      "item" : {
        "type" : "uri",
        "value" : "http://base.transformap.co/entity/Q80"
      },
      "subclass_of" : {
        "type" : "uri",
        "value" : "http://base.transformap.co/entity/Q30"
      },
      "instance_of" : {
        "type" : "uri",
        "value" : "http://base.transformap.co/entity/Q6"
      },
      "type_of_initiative_tag" : {
        "type" : "literal",
        "value" : "giveaway_shop"
      },
      "itemLabel" : {
        "xml:lang" : "de",
        "type" : "literal",
        "value" : "Umsonstladen"
      }
    }, {
      "item" : {
        "type" : "uri",
        "value" : "http://base.transformap.co/entity/Q81"
      },
      "subclass_of" : {
        "type" : "uri",
        "value" : "http://base.transformap.co/entity/Q30"
      },
      "instance_of" : {
        "type" : "uri",
        "value" : "http://base.transformap.co/entity/Q6"
      },
      "type_of_initiative_tag" : {
        "type" : "literal",
        "value" : "lending_central"
      },
      "itemLabel" : {
        "xml:lang" : "de",
        "type" : "literal",
        "value" : "Leihläden"
      }
    }, {
      "item" : {
        "type" : "uri",
        "value" : "http://base.transformap.co/entity/Q82"
      },
      "subclass_of" : {
        "type" : "uri",
        "value" : "http://base.transformap.co/entity/Q30"
      },
      "instance_of" : {
        "type" : "uri",
        "value" : "http://base.transformap.co/entity/Q6"
      },
      "type_of_initiative_tag" : {
        "type" : "literal",
        "value" : "swap_market"
      },
      "itemLabel" : {
        "xml:lang" : "de",
        "type" : "literal",
        "value" : "Tauschbörse"
      }
    }, {
      "item" : {
        "type" : "uri",
        "value" : "http://base.transformap.co/entity/Q83"
      },
      "subclass_of" : {
        "type" : "uri",
        "value" : "http://base.transformap.co/entity/Q30"
      },
      "instance_of" : {
        "type" : "uri",
        "value" : "http://base.transformap.co/entity/Q6"
      },
      "type_of_initiative_tag" : {
        "type" : "literal",
        "value" : "other_sharing"
      },
      "itemLabel" : {
        "xml:lang" : "de",
        "type" : "literal",
        "value" : "Andere (Umsonst- und Tauschökonomische Projekte)"
      }
    }, {
      "item" : {
        "type" : "uri",
        "value" : "http://base.transformap.co/entity/Q84"
      },
      "subclass_of" : {
        "type" : "uri",
        "value" : "http://base.transformap.co/entity/Q31"
      },
      "instance_of" : {
        "type" : "uri",
        "value" : "http://base.transformap.co/entity/Q6"
      },
      "type_of_initiative_tag" : {
        "type" : "literal",
        "value" : "repairing"
      },
      "itemLabel" : {
        "xml:lang" : "de",
        "type" : "literal",
        "value" : "Instandhaltung und Reparatur"
      }
    }, {
      "item" : {
        "type" : "uri",
        "value" : "http://base.transformap.co/entity/Q85"
      },
      "subclass_of" : {
        "type" : "uri",
        "value" : "http://base.transformap.co/entity/Q31"
      },
      "instance_of" : {
        "type" : "uri",
        "value" : "http://base.transformap.co/entity/Q6"
      },
      "type_of_initiative_tag" : {
        "type" : "literal",
        "value" : "repair_cafe"
      },
      "itemLabel" : {
        "xml:lang" : "de",
        "type" : "literal",
        "value" : "Repair Café"
      }
    }, {
      "item" : {
        "type" : "uri",
        "value" : "http://base.transformap.co/entity/Q86"
      },
      "subclass_of" : {
        "type" : "uri",
        "value" : "http://base.transformap.co/entity/Q31"
      },
      "instance_of" : {
        "type" : "uri",
        "value" : "http://base.transformap.co/entity/Q6"
      },
      "type_of_initiative_tag" : {
        "type" : "literal",
        "value" : "repair_resale"
      },
      "itemLabel" : {
        "xml:lang" : "de",
        "type" : "literal",
        "value" : "Wiederverkauf oder Reparatur von Gütern"
      }
    }, {
      "item" : {
        "type" : "uri",
        "value" : "http://base.transformap.co/entity/Q87"
      },
      "subclass_of" : {
        "type" : "uri",
        "value" : "http://base.transformap.co/entity/Q31"
      },
      "instance_of" : {
        "type" : "uri",
        "value" : "http://base.transformap.co/entity/Q6"
      },
      "type_of_initiative_tag" : {
        "type" : "literal",
        "value" : "other_repair"
      },
      "itemLabel" : {
        "xml:lang" : "de",
        "type" : "literal",
        "value" : "Andere (Reparaturprojekte und -initiativen)"
      }
    }, {
      "item" : {
        "type" : "uri",
        "value" : "http://base.transformap.co/entity/Q91"
      },
      "subclass_of" : {
        "type" : "uri",
        "value" : "http://base.transformap.co/entity/Q32"
      },
      "instance_of" : {
        "type" : "uri",
        "value" : "http://base.transformap.co/entity/Q6"
      },
      "type_of_initiative_tag" : {
        "type" : "literal",
        "value" : "recycling"
      },
      "itemLabel" : {
        "xml:lang" : "de",
        "type" : "literal",
        "value" : "Recycling"
      }
    }, {
      "item" : {
        "type" : "uri",
        "value" : "http://base.transformap.co/entity/Q92"
      },
      "subclass_of" : {
        "type" : "uri",
        "value" : "http://base.transformap.co/entity/Q32"
      },
      "instance_of" : {
        "type" : "uri",
        "value" : "http://base.transformap.co/entity/Q6"
      },
      "type_of_initiative_tag" : {
        "type" : "literal",
        "value" : "upcycling"
      },
      "itemLabel" : {
        "xml:lang" : "de",
        "type" : "literal",
        "value" : "Upcycling"
      }
    }, {
      "item" : {
        "type" : "uri",
        "value" : "http://base.transformap.co/entity/Q93"
      },
      "subclass_of" : {
        "type" : "uri",
        "value" : "http://base.transformap.co/entity/Q32"
      },
      "instance_of" : {
        "type" : "uri",
        "value" : "http://base.transformap.co/entity/Q6"
      },
      "type_of_initiative_tag" : {
        "type" : "literal",
        "value" : "eco_art"
      },
      "itemLabel" : {
        "xml:lang" : "de",
        "type" : "literal",
        "value" : "Naturkunst"
      }
    }, {
      "item" : {
        "type" : "uri",
        "value" : "http://base.transformap.co/entity/Q94"
      },
      "subclass_of" : {
        "type" : "uri",
        "value" : "http://base.transformap.co/entity/Q32"
      },
      "instance_of" : {
        "type" : "uri",
        "value" : "http://base.transformap.co/entity/Q6"
      },
      "type_of_initiative_tag" : {
        "type" : "literal",
        "value" : "other_reupcycle"
      },
      "itemLabel" : {
        "xml:lang" : "de",
        "type" : "literal",
        "value" : "Andere (Recycling- und Upcyclingprojekte)"
      }
    } ]
  }
}